CoralDBClient.py
CoralParallelClient.py
CoralParallelJob.py
CoralResultSet.py
MANIFEST.in
README.md
__init__.py
define.py
progressbar.py
serialize.py
setup.py
times.py
utils.py
version.py
../pycoraldb/CoralDBClient.py
../pycoraldb/CoralParallelClient.py
../pycoraldb/CoralParallelJob.py
../pycoraldb/CoralResultSet.py
../pycoraldb/README.md
../pycoraldb/__init__.py
../pycoraldb/define.py
../pycoraldb/progressbar.py
../pycoraldb/serialize.py
../pycoraldb/setup.py
../pycoraldb/times.py
../pycoraldb/utils.py
../pycoraldb/version.py
../pycoraldb.egg-info/PKG-INFO
../pycoraldb.egg-info/SOURCES.txt
../pycoraldb.egg-info/dependency_links.txt
../pycoraldb.egg-info/requires.txt
../pycoraldb.egg-info/top_level.txt
examples/__init__.py
examples/chapter2.01_get_user_spot_asset.py
examples/chapter2.02_get_user_spot_position.py
examples/chapter2.03_get_user_spot_order.py
examples/chapter2.04_get_user_spot_knock.py
examples/chapter2.05_get_user_future_asset.py
examples/chapter2.06_get_user_future_position.py
examples/chapter2.07_get_user_future_order.py
examples/chapter2.08_get_user_future_knock.py
examples/chapter2.09_get_user_option_asset.py
examples/chapter2.10_get_user_option_position.py
examples/chapter2.11_get_user_option_order.py
examples/chapter2.12_get_user_option_knock.py
examples/chapter3.01_callTs.py
examples/chapter3.02_callTsFunc.py
examples/chapter3.03_callTsFunc.py
examples/chapter4.01_setUserData.py
examples/chapter4.02_getUserData.py
examples/chapter4.03_delUserData.py
examples/chapter5.00_parallel.py
examples/chapter5.01_map.py
examples/chapter5.02_reduce.py
examples/chapter5.03_debug.py
examples/chapter5.04_progress.py
examples/test10_get_option_base_info.py
examples/test11_performance.py
examples/test1_login.py
examples/test2_change_password.py
examples/test3_get_trading_days.py
examples/test4_get_stat.py
examples/test5_get_code.py
examples/test6_get_bar.py
examples/test7_get_order.py
examples/test8_get_knock.py
examples/test9_get_notice.py
examples/test_parallel_map.py
examples/test_parallel_map_class.py
examples/test_parallel_reduce.py
pycoraldb.egg-info/PKG-INFO
pycoraldb.egg-info/SOURCES.txt
pycoraldb.egg-info/dependency_links.txt
pycoraldb.egg-info/requires.txt
pycoraldb.egg-info/top_level.txt
vendor/__init__.py
vendor/tqdm/__init__.py
vendor/tqdm/__main__.py
vendor/tqdm/_main.py
