Metadata-Version: 1.0
Name: pycoraldb
Version: 1.1.4.9
Summary: Python CoralDB Client
Home-page: https://pypi.python.org/pypi/pycoraldb
Author: FanCapital
Author-email: public@fancapital.com
License: FanCapital Public License
Keywords: pycoraldb coraldb
Platform: UNKNOWN
